davex/.schemawiz_config2
davex/.schemawiz_config3
davex/MySQLTableAnalysis.py
davex/PostgresTableAnalysis.py
davex/SimpleAnalysis.py
davex/TableAnalysis.py
davex/__init__.py
davex/alltables.csv
davex/cache_chart_counts.py
davex/help.py
davex/mysql_export.py
davex/mysql_extract.py
davex/mysql_import.py
davex/postgres_export.py
davex/postgres_extract.py
davex/postgres_import.py
davex/run.py
davex/sp_analyze.sql
davex/sp_setup.sql
davex/sqlite_export.py
davex/sqlite_extract.py
davex/sqlite_import.py
davex/sqliter.py
davex/supported_types.py
davex/test.py
davex-2.1.12.dist-info/METADATA
davex-2.1.12.dist-info/WHEEL
davex-2.1.12.dist-info/licenses/LICENSE
davex-2.1.12.dist-info/RECORD
